MANIFEST.in
setup.cfg
setup.py
marteau/__init__.py
marteau/client.py
marteau/config.py
marteau/fixtures.py
marteau/job.py
marteau/node.py
marteau/queue.py
marteau/redirector.py
marteau/runserver.py
marteau/util.py
marteau.egg-info/PKG-INFO
marteau.egg-info/SOURCES.txt
marteau.egg-info/dependency_links.txt
marteau.egg-info/entry_points.txt
marteau.egg-info/not-zip-safe
marteau.egg-info/requires.txt
marteau.egg-info/top_level.txt
marteau/docs/make.bat
marteau/docs/build/doctrees/environment.pickle
marteau/docs/build/doctrees/index.doctree
marteau/docs/build/html/.buildinfo
marteau/docs/build/html/genindex.html
marteau/docs/build/html/index.html
marteau/docs/build/html/objects.inv
marteau/docs/build/html/search.html
marteau/docs/build/html/searchindex.js
marteau/docs/build/html/_sources/index.txt
marteau/docs/build/html/_static/agogo.css
marteau/docs/build/html/_static/ajax-loader.gif
marteau/docs/build/html/_static/basic.css
marteau/docs/build/html/_static/bgfooter.png
marteau/docs/build/html/_static/bgtop.png
marteau/docs/build/html/_static/comment-bright.png
marteau/docs/build/html/_static/comment-close.png
marteau/docs/build/html/_static/comment.png
marteau/docs/build/html/_static/doctools.js
marteau/docs/build/html/_static/down-pressed.png
marteau/docs/build/html/_static/down.png
marteau/docs/build/html/_static/file.png
marteau/docs/build/html/_static/jquery.js
marteau/docs/build/html/_static/marteau.css
marteau/docs/build/html/_static/minus.png
marteau/docs/build/html/_static/plus.png
marteau/docs/build/html/_static/pygments.css
marteau/docs/build/html/_static/searchtools.js
marteau/docs/build/html/_static/underscore.js
marteau/docs/build/html/_static/up-pressed.png
marteau/docs/build/html/_static/up.png
marteau/docs/build/html/_static/websupport.js
marteau/docs/source/.conf.py.un~
marteau/docs/source/conf.py
marteau/docs/source/index.rst
marteau/docs/source/themes/marteau/theme.conf
marteau/docs/source/themes/marteau/static/marteau.css
marteau/media/.DS_Store
marteau/media/.marteau.css.un~
marteau/media/fade.png
marteau/media/head.png
marteau/media/jquery.js
marteau/media/jquery.textchange.min.js
marteau/media/logo.png
marteau/media/marteau.css
marteau/media/marteau.gif
