Metadata-Version: 1.0
Name: marteau
Version: 0.1
Summary: Hammer it.
Home-page: UNKNOWN
Author: Tarek Ziade
Author-email: tarek@ziade.org
License: UNKNOWN
Platform: UNKNOWN
Classifier: Programming Language :: Python
Classifier: License :: OSI Approved :: Apache Software License
Classifier: Development Status :: 1 - Planning
